sjson/__init__.py
sjson-2.1.1.dist-info/METADATA
sjson-2.1.1.dist-info/WHEEL
sjson-2.1.1.dist-info/licenses/LICENSE.txt
sjson-2.1.1.dist-info/RECORD
