Metadata-Version: 2.3
Name: SJSON
Version: 2.1.1
Summary: SJSON serializer/deserializer for Python
Project-URL: Homepage, http://sh13.net/projects/SJSON
Project-URL: Issue Tracker, https://github.com/anteru/sjson/issues
Project-URL: Repository, https://github.com/anteru/sjson
Author-email: "Matthäus G. Chajdas" <dev@anteru.net>
License: BSD 3-clause license
License-File: LICENSE.txt
Keywords: SJSON
Classifier: Development Status :: 6 - Mature
Classifier: Environment :: Console
Classifier: Intended Audience :: Developers
Classifier: License :: OSI Approved :: BSD License
Classifier: Natural Language :: English
Classifier: Operating System :: OS Independent
Classifier: Programming Language :: Python :: 3
Classifier: Programming Language :: Python :: 3.6
Classifier: Programming Language :: Python :: 3.7
Classifier: Programming Language :: Python :: 3.8
Classifier: Programming Language :: Python :: 3.9
Classifier: Programming Language :: Python :: 3.10
Classifier: Programming Language :: Python :: 3.11
Classifier: Programming Language :: Python :: 3.12
Classifier: Topic :: Software Development :: Libraries :: Python Modules
Requires-Python: >=3.6
